pygame_data/Camera Shake Controller.py
pygame_data/__init__.py
pygame_data/basic_module.py
pygame_data/coinscript.py
pygame_data/movescript.py
pygame_data/scorescript.py
pygame_data/scroll_module.py
pygame_data/shooter_module.py
pygame_data/snake_module.py
pygame_data/data/bg.png
pygame_data/data/coin.png
pygame_data/data/game character.png
pygame_data/data/game.png
pygame_data/data/ground.jpg
pygame_data/data/scene.png
pygame_data/data/snow imp instrution.txt
pygame_data/data/snow.png
pygame_data/data/ufo.png
pygame_data/data/wall.jpg
lib_pygames_data-0.1.dist-info/METADATA
lib_pygames_data-0.1.dist-info/WHEEL
lib_pygames_data-0.1.dist-info/top_level.txt
lib_pygames_data-0.1.dist-info/RECORD
